qtpi_test_kernel/__init__.py
qtpi_test_kernel/__main__.py
qtpi_test_kernel/install.py
qtpi_test_kernel/kernel.py
qtpi_test_kernel-0.1.4.dist-info/LICENSE
qtpi_test_kernel-0.1.4.dist-info/METADATA
qtpi_test_kernel-0.1.4.dist-info/WHEEL
qtpi_test_kernel-0.1.4.dist-info/top_level.txt
qtpi_test_kernel-0.1.4.dist-info/RECORD
