Metadata-Version: 2.1
Name: qtpi-test-kernel
Version: 0.1.4
Summary: Simple example of qtpi test kernel python wrapper for Jupyter to enable Qtpi quantum language
Home-page: https://github.com/miroslav14/qtpi_test_kernel.git
Author: Jupyter Development Team
Author-email: jupyter@googlegroups.com
License: UNKNOWN
Platform: UNKNOWN
Classifier: Intended Audience :: Developers
Classifier: License :: OSI Approved :: BSD License
Classifier: Programming Language :: Python :: 3
Requires-Dist: jupyter-client
Requires-Dist: IPython
Requires-Dist: ipykernel
